<?xml version="1.0" encoding="utf-8"?>
<!-- Copyright 2015 PLEN project. All rights reserved. -->
<UI type="basic">
    <Mode type="basic" name="Normal" image="p_mode_normal" pressed="p_mode_normal_pressed">
        <Command type="Button">
            <Action key="0" name="0" value="$PM00" image="p_normal_lstep" pressed="p_normal_lstep_pressed"/>
            <Action key="1" name="1" value="$PM01" image="p_normal_onestep" pressed="p_normal_onestep_pressed"/>
            <Action key="2" name="2" value="$PM02" image="p_normal_rstep" pressed="p_normal_rstep_pressed"/>
            <Action key="3" name="3" value="$PM03" image="p_normal_ehen" pressed="p_normal_ehen_pressed"/>
            <Action key="4" name="4" value="$PM04" image="p_normal_hello" pressed="p_normal_hello_pressed"/>
            <Action key="5" name="5" value="$PM05" image="p_normal_love" pressed="p_normal_love_pressed"/>
            <Action key="6" name="6" value="$PM06" image="p_normal_hug" pressed="p_normal_hug_pressed"/>
            <Action key="7" name="7" value="$PM07" image="p_normal_handclap" pressed="p_normal_handclap_pressed"/>
            <Action key="8" name="8" value="$PM08" image="p_normal_hitouch" pressed="p_normal_hitouch_pressed"/>
        </Command>
        <Command type="Wheel">
            <Action key="up" value="$PM46" />
            <Action key="center" value="$SM$SM" />
            <Action key="down" value="$PM49" />
            <Action key="left" value="$PM47" />
            <Action key="right" value="$PM48" />
        </Command>
    </Mode>
    <Mode type="basic" name="Box" image="p_mode_box" pressed="p_mode_box_pressed">
        <Command type="Button">
            <Action key="0" name="b0" value="$PM0A" image="p_box_shake" pressed="p_box_shake_pressed"/>
            <Action key="1" name="b1" value="$PM0B" image="p_box_lift_high" pressed="p_box_lift_high_pressed"/>
            <Action key="2" name="b2" value="$PM0C" image="p_box_lift_low" pressed="p_box_lift_low_pressed"/>
            <Action key="3" name="b3" value="$PM0D" image="p_box_receive" pressed="p_box_receive_pressed"/>
            <Action key="4" name="b4" value="$PM0E" image="p_box_holdup" pressed="p_box_holdup_pressed"/>
            <Action key="5" name="b5" value="$PM0F" image="p_box_give" pressed="p_box_give_pressed"/>
            <Action key="6" name="b6" value="$PM10" image="p_box_throw" pressed="p_box_throw_pressed"/>
            <Action key="7" name="b7" value="$PM11" image="p_box_takedown_high" pressed="p_box_takedown_high_pressed"/>
            <Action key="8" name="b8" value="$PM12" image="p_box_takedown_low" pressed="p_box_takedown_low_pressed"/>
        </Command>
        <Command type="Wheel">
            <Action key="up" value="$PM4A" />
            <Action key="center" value="$SM$SM" />
            <Action key="down" value="$PM4D" />
            <Action key="left" value="$PM4B" />
            <Action key="right" value="$PM4C" />
        </Command>
    </Mode>
    <Mode type="basic" name="Soccer" image="p_mode_soccer" pressed="p_mode_soccer_pressed">
        <Command type="Button">
            <Action key="0" name="s0" value="$PM14" image="p_normal_lstep" pressed="p_normal_lstep_pressed"/>
            <Action key="1" name="s1" value="$PM15" image="p_normal_onestep" pressed="p_normal_onestep_pressed"/>
            <Action key="2" name="s2" value="$PM16" image="p_normal_rstep" pressed="p_normal_rstep_pressed"/>
            <Action key="3" name="s3" value="$PM17" image="p_soccer_l_kick" pressed="p_soccer_l_kick_pressed"/>
            <Action key="4" name="s4" value="$PM18" image="p_soccer_5dash" pressed="p_soccer_5dash_pressed"/>
            <Action key="5" name="s5" value="$PM19" image="p_soccer_r_kick" pressed="p_soccer_r_kick_pressed"/>
            <Action key="6" name="s6" value="$PM1A" image="p_soccer_l_pass" pressed="p_soccer_l_pass_pressed"/>
            <Action key="7" name="s7" value="$PM1B" image="p_normal_handclap" pressed="p_normal_handclap_pressed"/>
            <Action key="8" name="s8" value="$PM1C" image="p_soccer_r_pass" pressed="p_soccer_r_pass_pressed"/>
        </Command>
        <Command type="Wheel">
            <Action key="up" value="$PM46" />
            <Action key="center" value="$SM$SM" />
            <Action key="down" value="$PM49" />
            <Action key="left" value="$PM47" />
            <Action key="right" value="$PM48" />
        </Command>
    </Mode>
    <Mode type="basic" name="Dance" image="p_mode_dance" pressed="p_mode_dance_pressed">
        <Command type="Button">
            <Action key="0" name="m0" value="$PM1E" image="p_dance_rhythm_lstep" pressed="p_dance_rhythm_lstep_pressed"/>
            <Action key="1" name="m1" value="$PM1F" image="p_dance_rhythm_onestep" pressed="p_dance_rhythm_onestep_pressed"/>
            <Action key="2" name="m2" value="$PM20" image="p_dance_rhythm_rstep" pressed="p_dance_rhythm_rstep_pressed"/>
            <Action key="3" name="m3" value="$PM21" image="p_dance_kimepose" pressed="p_dance_kimepose_pressed"/>
            <Action key="4" name="m4" value="$PM22" image="p_dance_kusshin" pressed="p_dance_kusshin_pressed"/>
            <Action key="5" name="m5" value="$PM23" image="p_dance_rhythm" pressed="p_dance_rhythm_pressed"/>
            <Action key="6" name="m6" value="$PM24" image="p_dance_rhythm_back" pressed="p_dance_rhythm_back_pressed"/>
            <Action key="7" name="m7" value="$PM25" image="p_normal_hello" pressed="p_normal_hello_pressed"/>
            <Action key="8" name="m8" value="$PM26" image="p_dance_twist" pressed="p_dance_twist_pressed"/>
        </Command>
        <Command type="Wheel">
            <Action key="up" value="$PM46" />
            <Action key="center" value="$SM$SM" />
            <Action key="down" value="$PM49" />
            <Action key="left" value="$PM47" />
            <Action key="right" value="$PM48" />
        </Command>
    </Mode>
    <Mode type="basic" name="Skate" image="p_mode_skate" pressed="p_mode_skate_pressed">
        <Command type="Button">
            <Action key="0" name="sk0" value="$PM28" image="p_skate_l_balance" pressed="p_skate_l_balance_pressed"/>
            <Action key="1" name="sk1" value="$PM29" image="p_skate_mae_brake" pressed="p_skate_mae_brake_pressed"/>
            <Action key="2" name="sk2" value="$PM2A" image="p_skate_r_balance" pressed="p_skate_r_balance_pressed"/>
            <Action key="3" name="sk3" value="$PM2B" image="p_skate_l_t_balance" pressed="p_skate_l_t_balance_pressed"/>
            <Action key="4" name="sk4" value="$PM2C" image="p_skate_chokuritsu" pressed="p_skate_chokuritsu_pressed"/>
            <Action key="5" name="sk5" value="$PM2D" image="p_skate_r_t_balance" pressed="p_skate_r_t_balance_pressed"/>
            <Action key="6" name="sk6" value="$PM2E" image="p_skate_l_tsumasaki" pressed="p_skate_l_tsumasaki_pressed"/>
            <Action key="7" name="sk7" value="$PM2F" image="p_skate_ushiro_brake" pressed="p_skate_ushiro_brake_pressed"/>
            <Action key="8" name="sk8" value="$PM30" image="p_skate_r_tsumasaki" pressed="p_skate_r_tsumasaki_pressed"/>
        </Command>
        <Command type="Wheel">
            <Action key="up" value="$PM4E" />
            <Action key="center" value="$SM$SM" />
            <Action key="down" value="$PM51" />
            <Action key="left" value="$PM4F" />
            <Action key="right" value="$PM50" />
        </Command>
    </Mode>
</UI>
